cfblog/__init__.py
cfblog/admin.py
cfblog/managers.py
cfblog/middleware.py
cfblog/models.py
cfblog/response.py
cfblog/signals.py
cfblog/tests.py
cfblog/urls.py
cfblog/utils.py
cfblog/validators.py
cfblog/views.py
cfblog/conf/__init__.py
cfblog/conf/global_settings.py
cfblog/migrations/0001_initial.py
cfblog/migrations/0002_create_static_page_category.py
cfblog/migrations/0003_auto_20151126_1212.py
cfblog/migrations/0004_auto_20160406_1820.py
cfblog/migrations/0005_auto_20160406_1825.py
cfblog/migrations/0006_category_is_static.py
cfblog/migrations/0007_category_url.py
cfblog/migrations/0008_populate_category_url.py
cfblog/migrations/__init__.py
cfblog/static/cfblog/js/edit.js
cfblog/static/cfblog/js/edit.min.js
cfblog/templates/cfblog_base.html
cfblog/templates/cfblog_admin/script.html
cfblog/templates/cfblog_admin/toolbar.html
cfblog/templates/cms_templates/snippet.html
cfblog/templates/cms_templates/snippet_2.html
cfblog/templates/cms_templates/template_1.html
cfblog-0.2.16.dist-info/DESCRIPTION.rst
cfblog-0.2.16.dist-info/METADATA
cfblog-0.2.16.dist-info/RECORD
cfblog-0.2.16.dist-info/WHEEL
cfblog-0.2.16.dist-info/metadata.json
cfblog-0.2.16.dist-info/top_level.txt
cfblog-0.2.16.dist-info/zip-safe
