Metadata-Version: 2.0
Name: cfblog
Version: 0.2.16
Summary: Awesome CMS for Django
Home-page: https://github.com/Coverfox/cfblog/
Author: Vinay Karanam, Ashish Nayan
Author-email: vinayinvicible@gmail.com, nayanashish@gmail.com
License: BSD
Platform: UNKNOWN
Classifier: Development Status :: 4 - Beta
Classifier: Environment :: Web Environment
Classifier: Framework :: Django :: 1.8
Classifier: Framework :: Django :: 1.9
Classifier: Framework :: Django :: 1.10
Classifier: Framework :: Django :: 1.11
Classifier: License :: OSI Approved :: BSD License
Classifier: Programming Language :: Python :: 2.7
Classifier: Programming Language :: Python :: 3.5
Classifier: Programming Language :: Python :: 3.6
Requires-Dist: beautifulsoup4
Requires-Dist: jsonfield
Requires-Dist: django-tagging
Requires-Dist: mistune
